{"edge_status": "Up", "origin_status": "Up", "edge_response_times": [{"time": "2025-06-21 14:00:00", "region": "apac", "response_time": 24.848399999999998}, {"time": "2025-06-21 14:15:00", "region": "apac", "response_time": 30.638035666666664}, {"time": "2025-06-21 14:30:00", "region": "apac", "response_time": 39.30300866666666}, {"time": "2025-06-21 14:45:00", "region": "apac", "response_time": 29.731696666666664}, {"time": "2025-06-21 15:00:00", "region": "apac", "response_time": 44.218654}, {"time": "2025-06-21 15:15:00", "region": "apac", "response_time": 29.995182333333332}, {"time": "2025-06-21 15:30:00", "region": "apac", "response_time": 30.273881333333335}, {"time": "2025-06-21 15:45:00", "region": "apac", "response_time": 15.990856}, {"time": "2025-06-21 16:00:00", "region": "apac", "response_time": 16.345214666666667}, {"time": "2025-06-21 16:15:00", "region": "apac", "response_time": 28.857861999999997}, {"time": "2025-06-21 16:30:00", "region": "apac", "response_time": 20.316072666666667}, {"time": "2025-06-21 16:45:00", "region": "apac", "response_time": 247.06786766666667}, {"time": "2025-06-21 17:00:00", "region": "apac", "response_time": 451.7902303333334}, {"time": "2025-06-21 17:15:00", "region": "apac", "response_time": 28.665011666666672}, {"time": "2025-06-21 17:30:00", "region": "apac", "response_time": 17.687636}, {"time": "2025-06-21 17:45:00", "region": "apac", "response_time": 34.34013866666667}, {"time": "2025-06-21 18:00:00", "region": "apac", "response_time": 54.496399000000004}, {"time": "2025-06-21 18:15:00", "region": "apac", "response_time": 39.11192333333333}, {"time": "2025-06-21 18:30:00", "region": "apac", "response_time": 16.144519666666667}, {"time": "2025-06-21 18:45:00", "region": "apac", "response_time": 30.111479}, {"time": "2025-06-21 19:00:00", "region": "apac", "response_time": 14.577405666666667}, {"time": "2025-06-21 19:15:00", "region": "apac", "response_time": 59.28904066666667}, {"time": "2025-06-21 19:30:00", "region": "apac", "response_time": 16.871171333333333}, {"time": "2025-06-21 19:45:00", "region": "apac", "response_time": 18.736515999999998}, {"time": "2025-06-21 19:56:13", "region": "apac", "response_time": 334.800483}, {"time": "2025-06-21 14:00:00", "region": "eu-west", "response_time": 28.256603000000002}, {"time": "2025-06-21 14:15:00", "region": "eu-west", "response_time": 19.15811833333333}, {"time": "2025-06-21 14:30:00", "region": "eu-west", "response_time": 22.44660233333333}, {"time": "2025-06-21 14:45:00", "region": "eu-west", "response_time": 19.611757666666662}, {"time": "2025-06-21 15:00:00", "region": "eu-west", "response_time": 20.405399000000003}, {"time": "2025-06-21 15:15:00", "region": "eu-west", "response_time": 34.199967}, {"time": "2025-06-21 15:30:00", "region": "eu-west", "response_time": 26.231170666666664}, {"time": "2025-06-21 15:45:00", "region": "eu-west", "response_time": 27.711488333333335}, {"time": "2025-06-21 16:00:00", "region": "eu-west", "response_time": 28.12619966666667}, {"time": "2025-06-21 16:15:00", "region": "eu-west", "response_time": 25.68132466666666}, {"time": "2025-06-21 16:30:00", "region": "eu-west", "response_time": 18.632977666666665}, {"time": "2025-06-21 16:45:00", "region": "eu-west", "response_time": 1501.7655676666666}, {"time": "2025-06-21 17:00:00", "region": "eu-west", "response_time": 23.401295}, {"time": "2025-06-21 17:15:00", "region": "eu-west", "response_time": 21.23811033333334}, {"time": "2025-06-21 17:30:00", "region": "eu-west", "response_time": 26.342775666666668}, {"time": "2025-06-21 17:45:00", "region": "eu-west", "response_time": 24.307297000000002}, {"time": "2025-06-21 18:00:00", "region": "eu-west", "response_time": 156.33205333333333}, {"time": "2025-06-21 18:15:00", "region": "eu-west", "response_time": 25.100757333333334}, {"time": "2025-06-21 18:30:00", "region": "eu-west", "response_time": 25.250404333333332}, {"time": "2025-06-21 18:45:00", "region": "eu-west", "response_time": 20.796110000000002}, {"time": "2025-06-21 19:00:00", "region": "eu-west", "response_time": 23.496915666666663}, {"time": "2025-06-21 19:15:00", "region": "eu-west", "response_time": 30.735641666666663}, {"time": "2025-06-21 19:30:00", "region": "eu-west", "response_time": 29.53036433333334}, {"time": "2025-06-21 19:45:00", "region": "eu-west", "response_time": 28.717094333333332}, {"time": "2025-06-21 19:56:13", "region": "eu-west", "response_time": 14.817429}, {"time": "2025-06-21 14:00:00", "region": "us-east", "response_time": 67.33985000000001}, {"time": "2025-06-21 14:15:00", "region": "us-east", "response_time": 65.21030066666667}, {"time": "2025-06-21 14:30:00", "region": "us-east", "response_time": 70.568269}, {"time": "2025-06-21 14:45:00", "region": "us-east", "response_time": 109.29898733333333}, {"time": "2025-06-21 15:00:00", "region": "us-east", "response_time": 62.822362000000005}, {"time": "2025-06-21 15:15:00", "region": "us-east", "response_time": 75.26434233333333}, {"time": "2025-06-21 15:30:00", "region": "us-east", "response_time": 92.96225000000001}, {"time": "2025-06-21 15:45:00", "region": "us-east", "response_time": 104.69197633333334}, {"time": "2025-06-21 16:00:00", "region": "us-east", "response_time": 89.51455133333334}, {"time": "2025-06-21 16:15:00", "region": "us-east", "response_time": 82.90904033333334}, {"time": "2025-06-21 16:30:00", "region": "us-east", "response_time": 99.64363999999999}, {"time": "2025-06-21 16:45:00", "region": "us-east", "response_time": 69.34500766666666}, {"time": "2025-06-21 17:00:00", "region": "us-east", "response_time": 108.65911566666668}, {"time": "2025-06-21 17:15:00", "region": "us-east", "response_time": 239.34923733333332}, {"time": "2025-06-21 17:30:00", "region": "us-east", "response_time": 87.47605733333334}, {"time": "2025-06-21 17:45:00", "region": "us-east", "response_time": 88.83665633333334}, {"time": "2025-06-21 18:00:00", "region": "us-east", "response_time": 83.700774}, {"time": "2025-06-21 18:15:00", "region": "us-east", "response_time": 76.25562033333334}, {"time": "2025-06-21 18:30:00", "region": "us-east", "response_time": 109.50152533333333}, {"time": "2025-06-21 18:45:00", "region": "us-east", "response_time": 103.40388166666665}, {"time": "2025-06-21 19:00:00", "region": "us-east", "response_time": 110.90644333333333}, {"time": "2025-06-21 19:15:00", "region": "us-east", "response_time": 98.32167333333335}, {"time": "2025-06-21 19:30:00", "region": "us-east", "response_time": 149.151941}, {"time": "2025-06-21 19:45:00", "region": "us-east", "response_time": 81.114036}, {"time": "2025-06-21 19:56:13", "region": "us-east", "response_time": 269.458694}, {"time": "2025-06-21 14:15:00", "region": "us-west", "response_time": 60.31378466666667}, {"time": "2025-06-21 14:30:00", "region": "us-west", "response_time": 28.424341333333334}, {"time": "2025-06-21 14:45:00", "region": "us-west", "response_time": 23.581990666666666}, {"time": "2025-06-21 15:00:00", "region": "us-west", "response_time": 24.465720666666666}, {"time": "2025-06-21 15:15:00", "region": "us-west", "response_time": 28.968017333333332}, {"time": "2025-06-21 15:30:00", "region": "us-west", "response_time": 20.449204666666667}, {"time": "2025-06-21 15:45:00", "region": "us-west", "response_time": 25.117127666666665}, {"time": "2025-06-21 16:00:00", "region": "us-west", "response_time": 44.978734333333335}, {"time": "2025-06-21 16:15:00", "region": "us-west", "response_time": 25.453635333333335}, {"time": "2025-06-21 16:30:00", "region": "us-west", "response_time": 20.502709666666668}, {"time": "2025-06-21 16:45:00", "region": "us-west", "response_time": 44.52705}, {"time": "2025-06-21 17:00:00", "region": "us-west", "response_time": 567.712931}, {"time": "2025-06-21 17:15:00", "region": "us-west", "response_time": 215.48024333333336}, {"time": "2025-06-21 17:30:00", "region": "us-west", "response_time": 44.177007999999994}, {"time": "2025-06-21 17:45:00", "region": "us-west", "response_time": 21.078003666666664}, {"time": "2025-06-21 18:00:00", "region": "us-west", "response_time": 19.343176}, {"time": "2025-06-21 18:15:00", "region": "us-west", "response_time": 21.719143}, {"time": "2025-06-21 18:30:00", "region": "us-west", "response_time": 22.94769}, {"time": "2025-06-21 18:45:00", "region": "us-west", "response_time": 22.757103333333333}, {"time": "2025-06-21 19:00:00", "region": "us-west", "response_time": 25.799186000000002}, {"time": "2025-06-21 19:15:00", "region": "us-west", "response_time": 44.77130466666666}, {"time": "2025-06-21 19:30:00", "region": "us-west", "response_time": 29.017981999999996}, {"time": "2025-06-21 19:45:00", "region": "us-west", "response_time": 27.612405333333335}, {"time": "2025-06-21 19:56:13", "region": "us-west", "response_time": 197.4973156666667}], "origin_response_times": [{"time": "2025-06-21 14:00:00", "region": "apac", "response_time": 522.274663}, {"time": "2025-06-21 14:15:00", "region": "apac", "response_time": 573.3388213333334}, {"time": "2025-06-21 14:30:00", "region": "apac", "response_time": 507.3829496666668}, {"time": "2025-06-21 14:45:00", "region": "apac", "response_time": 502.77198766666663}, {"time": "2025-06-21 15:00:00", "region": "apac", "response_time": 1380.5402943333333}, {"time": "2025-06-21 15:15:00", "region": "apac", "response_time": 503.5875253333333}, {"time": "2025-06-21 15:30:00", "region": "apac", "response_time": 490.59037433333333}, {"time": "2025-06-21 15:45:00", "region": "apac", "response_time": 503.5388803333333}, {"time": "2025-06-21 16:00:00", "region": "apac", "response_time": 490.764353}, {"time": "2025-06-21 16:15:00", "region": "apac", "response_time": 872.1953123333334}, {"time": "2025-06-21 16:30:00", "region": "apac", "response_time": 510.0012886666666}, {"time": "2025-06-21 16:45:00", "region": "apac", "response_time": 516.026225}, {"time": "2025-06-21 17:00:00", "region": "apac", "response_time": 551.8910656666667}, {"time": "2025-06-21 17:15:00", "region": "apac", "response_time": 501.4339376666667}, {"time": "2025-06-21 17:30:00", "region": "apac", "response_time": 487.50309866666663}, {"time": "2025-06-21 17:45:00", "region": "apac", "response_time": 482.53146966666674}, {"time": "2025-06-21 18:00:00", "region": "apac", "response_time": 514.0767226666667}, {"time": "2025-06-21 18:15:00", "region": "apac", "response_time": 528.9187646666668}, {"time": "2025-06-21 18:30:00", "region": "apac", "response_time": 513.123605}, {"time": "2025-06-21 18:45:00", "region": "apac", "response_time": 525.9541436666667}, {"time": "2025-06-21 19:00:00", "region": "apac", "response_time": 509.90451733333333}, {"time": "2025-06-21 19:15:00", "region": "apac", "response_time": 516.1253576666667}, {"time": "2025-06-21 19:30:00", "region": "apac", "response_time": 505.8819436666667}, {"time": "2025-06-21 19:45:00", "region": "apac", "response_time": 509.3832313333333}, {"time": "2025-06-21 19:56:13", "region": "apac", "response_time": 497.45131649999996}, {"time": "2025-06-21 14:00:00", "region": "eu-west", "response_time": 61.065893}, {"time": "2025-06-21 14:15:00", "region": "eu-west", "response_time": 54.214775}, {"time": "2025-06-21 14:30:00", "region": "eu-west", "response_time": 53.22163766666666}, {"time": "2025-06-21 14:45:00", "region": "eu-west", "response_time": 56.41850833333334}, {"time": "2025-06-21 15:00:00", "region": "eu-west", "response_time": 56.139480999999996}, {"time": "2025-06-21 15:15:00", "region": "eu-west", "response_time": 54.42971}, {"time": "2025-06-21 15:30:00", "region": "eu-west", "response_time": 54.338060333333324}, {"time": "2025-06-21 15:45:00", "region": "eu-west", "response_time": 56.39090833333333}, {"time": "2025-06-21 16:00:00", "region": "eu-west", "response_time": 57.135172000000004}, {"time": "2025-06-21 16:15:00", "region": "eu-west", "response_time": 55.09330933333334}, {"time": "2025-06-21 16:30:00", "region": "eu-west", "response_time": 57.21693366666666}, {"time": "2025-06-21 16:45:00", "region": "eu-west", "response_time": 58.12986}, {"time": "2025-06-21 17:00:00", "region": "eu-west", "response_time": 57.47547833333333}, {"time": "2025-06-21 17:15:00", "region": "eu-west", "response_time": 55.10969299999999}, {"time": "2025-06-21 17:30:00", "region": "eu-west", "response_time": 58.94291666666667}, {"time": "2025-06-21 17:45:00", "region": "eu-west", "response_time": 55.49046866666666}, {"time": "2025-06-21 18:00:00", "region": "eu-west", "response_time": 58.24764633333333}, {"time": "2025-06-21 18:15:00", "region": "eu-west", "response_time": 53.853639}, {"time": "2025-06-21 18:30:00", "region": "eu-west", "response_time": 54.89090566666666}, {"time": "2025-06-21 18:45:00", "region": "eu-west", "response_time": 58.80294633333333}, {"time": "2025-06-21 19:00:00", "region": "eu-west", "response_time": 54.849547}, {"time": "2025-06-21 19:15:00", "region": "eu-west", "response_time": 53.20498666666667}, {"time": "2025-06-21 19:30:00", "region": "eu-west", "response_time": 55.00776233333334}, {"time": "2025-06-21 19:45:00", "region": "eu-west", "response_time": 55.435000666666674}, {"time": "2025-06-21 19:56:13", "region": "eu-west", "response_time": 55.751191500000004}, {"time": "2025-06-21 14:00:00", "region": "us-east", "response_time": 315.924301}, {"time": "2025-06-21 14:15:00", "region": "us-east", "response_time": 302.88471266666664}, {"time": "2025-06-21 14:30:00", "region": "us-east", "response_time": 309.59385833333334}, {"time": "2025-06-21 14:45:00", "region": "us-east", "response_time": 322.44111933333335}, {"time": "2025-06-21 15:00:00", "region": "us-east", "response_time": 306.954655}, {"time": "2025-06-21 15:15:00", "region": "us-east", "response_time": 315.2790433333333}, {"time": "2025-06-21 15:30:00", "region": "us-east", "response_time": 315.84500033333336}, {"time": "2025-06-21 15:45:00", "region": "us-east", "response_time": 342.875003}, {"time": "2025-06-21 16:00:00", "region": "us-east", "response_time": 367.330299}, {"time": "2025-06-21 16:15:00", "region": "us-east", "response_time": 323.8204866666667}, {"time": "2025-06-21 16:30:00", "region": "us-east", "response_time": 298.09285700000004}, {"time": "2025-06-21 16:45:00", "region": "us-east", "response_time": 324.5227896666667}, {"time": "2025-06-21 17:00:00", "region": "us-east", "response_time": 335.85196066666674}, {"time": "2025-06-21 17:15:00", "region": "us-east", "response_time": 312.12164466666667}, {"time": "2025-06-21 17:30:00", "region": "us-east", "response_time": 298.34433499999994}, {"time": "2025-06-21 17:45:00", "region": "us-east", "response_time": 317.62018200000006}, {"time": "2025-06-21 18:00:00", "region": "us-east", "response_time": 308.11362933333334}, {"time": "2025-06-21 18:15:00", "region": "us-east", "response_time": 321.4968583333333}, {"time": "2025-06-21 18:30:00", "region": "us-east", "response_time": 306.5593886666667}, {"time": "2025-06-21 18:45:00", "region": "us-east", "response_time": 314.315541}, {"time": "2025-06-21 19:00:00", "region": "us-east", "response_time": 347.206834}, {"time": "2025-06-21 19:15:00", "region": "us-east", "response_time": 325.92149033333334}, {"time": "2025-06-21 19:30:00", "region": "us-east", "response_time": 303.973682}, {"time": "2025-06-21 19:45:00", "region": "us-east", "response_time": 309.12933999999996}, {"time": "2025-06-21 19:56:13", "region": "us-east", "response_time": 306.99461299999996}, {"time": "2025-06-21 14:15:00", "region": "us-west", "response_time": 438.00593433333336}, {"time": "2025-06-21 14:30:00", "region": "us-west", "response_time": 432.2031723333333}, {"time": "2025-06-21 14:45:00", "region": "us-west", "response_time": 419.8002373333333}, {"time": "2025-06-21 15:00:00", "region": "us-west", "response_time": 434.55667866666676}, {"time": "2025-06-21 15:15:00", "region": "us-west", "response_time": 421.4026323333333}, {"time": "2025-06-21 15:30:00", "region": "us-west", "response_time": 420.6185586666667}, {"time": "2025-06-21 15:45:00", "region": "us-west", "response_time": 434.4635643333333}, {"time": "2025-06-21 16:00:00", "region": "us-west", "response_time": 432.341992}, {"time": "2025-06-21 16:15:00", "region": "us-west", "response_time": 421.7939886666667}, {"time": "2025-06-21 16:30:00", "region": "us-west", "response_time": 426.25158933333336}, {"time": "2025-06-21 16:45:00", "region": "us-west", "response_time": 446.98514100000006}, {"time": "2025-06-21 17:00:00", "region": "us-west", "response_time": 412.4121623333334}, {"time": "2025-06-21 17:15:00", "region": "us-west", "response_time": 437.3115376666667}, {"time": "2025-06-21 17:30:00", "region": "us-west", "response_time": 420.2483563333333}, {"time": "2025-06-21 17:45:00", "region": "us-west", "response_time": 437.765261}, {"time": "2025-06-21 18:00:00", "region": "us-west", "response_time": 426.58749666666665}, {"time": "2025-06-21 18:15:00", "region": "us-west", "response_time": 410.50624933333336}, {"time": "2025-06-21 18:30:00", "region": "us-west", "response_time": 435.9000056666667}, {"time": "2025-06-21 18:45:00", "region": "us-west", "response_time": 434.16106233333335}, {"time": "2025-06-21 19:00:00", "region": "us-west", "response_time": 426.65163}, {"time": "2025-06-21 19:15:00", "region": "us-west", "response_time": 430.57518566666664}, {"time": "2025-06-21 19:30:00", "region": "us-west", "response_time": 432.1784833333333}, {"time": "2025-06-21 19:45:00", "region": "us-west", "response_time": 420.421848}, {"time": "2025-06-21 19:56:13", "region": "us-west", "response_time": 423.71534033333336}], "edge_responses_by_region": [{"region": "apac", "min": 13.157164, "max": 653.2009509999999, "mean": 64.41845520833334, "p95": 355.5295979999999}, {"region": "eu-west", "min": 14.250594999999999, "max": 4469.894058000001, "mean": 91.60485606944445, "p95": 42.76156289999994}, {"region": "us-east", "min": 46.626099999999994, "max": 500.301957, "mean": 102.5413931111111, "p95": 175.49886569999975}, {"region": "us-west", "min": 13.652531000000002, "max": 582.401558, "mean": 66.94565868055555, "p95": 551.1636458}], "origin_responses_by_region": [{"region": "apac", "min": 471.3386, "max": 1721.2331629999999, "mean": 562.6329847916667, "p95": 700.4745647999991}, {"region": "eu-west", "min": 48.926978000000005, "max": 63.086774, "mean": 55.89842104166666, "p95": 61.0607427}, {"region": "us-east", "min": 275.53791, "max": 409.613714, "mean": 318.3444119166667, "p95": 378.03454360000006}, {"region": "us-west", "min": 393.97523, "max": 503.937259, "mean": 428.2024211527778, "p95": 446.783188}], "services": [["https://www.bentasker.co.uk/", "Unknown"], ["https://mastodon.bentasker.co.uk/", "Unknown"]]}