{"edge_status": "Up", "origin_status": "Up", "edge_response_times": [{"time": "2024-07-12 18:00:00", "region": "apac", "response_time": 56.746903999999994}, {"time": "2024-07-12 18:15:00", "region": "apac", "response_time": 64.736336}, {"time": "2024-07-12 18:30:00", "region": "apac", "response_time": 19.189631666666664}, {"time": "2024-07-12 18:45:00", "region": "apac", "response_time": 22.903419666666665}, {"time": "2024-07-12 19:00:00", "region": "apac", "response_time": 40.45401166666667}, {"time": "2024-07-12 19:15:00", "region": "apac", "response_time": 33.753689333333334}, {"time": "2024-07-12 19:30:00", "region": "apac", "response_time": 66.67291166666666}, {"time": "2024-07-12 19:45:00", "region": "apac", "response_time": 15.91651366666667}, {"time": "2024-07-12 20:00:00", "region": "apac", "response_time": 18.966858333333334}, {"time": "2024-07-12 20:15:00", "region": "apac", "response_time": 18.27255866666667}, {"time": "2024-07-12 20:30:00", "region": "apac", "response_time": 15.528721333333335}, {"time": "2024-07-12 20:45:00", "region": "apac", "response_time": 77.47485}, {"time": "2024-07-12 21:00:00", "region": "apac", "response_time": 23.306931}, {"time": "2024-07-12 21:15:00", "region": "apac", "response_time": 45.733757000000004}, {"time": "2024-07-12 21:30:00", "region": "apac", "response_time": 42.50798733333333}, {"time": "2024-07-12 21:45:00", "region": "apac", "response_time": 29.828542666666667}, {"time": "2024-07-12 22:00:00", "region": "apac", "response_time": 32.22978566666667}, {"time": "2024-07-12 22:15:00", "region": "apac", "response_time": 21.359410333333333}, {"time": "2024-07-12 22:30:00", "region": "apac", "response_time": 64.67248833333333}, {"time": "2024-07-12 22:45:00", "region": "apac", "response_time": 43.455102999999994}, {"time": "2024-07-12 23:00:00", "region": "apac", "response_time": 13.510718333333333}, {"time": "2024-07-12 23:15:00", "region": "apac", "response_time": 46.37773966666667}, {"time": "2024-07-12 23:30:00", "region": "apac", "response_time": 63.529191999999995}, {"time": "2024-07-12 23:45:00", "region": "apac", "response_time": 61.79432266666667}, {"time": "2024-07-12 18:00:00", "region": "eu-west", "response_time": 28.765342333333333}, {"time": "2024-07-12 18:15:00", "region": "eu-west", "response_time": 30.806322}, {"time": "2024-07-12 18:30:00", "region": "eu-west", "response_time": 41.509943666666665}, {"time": "2024-07-12 18:45:00", "region": "eu-west", "response_time": 30.69574333333333}, {"time": "2024-07-12 19:00:00", "region": "eu-west", "response_time": 43.427303333333334}, {"time": "2024-07-12 19:15:00", "region": "eu-west", "response_time": 42.80140600000001}, {"time": "2024-07-12 19:30:00", "region": "eu-west", "response_time": 32.124525}, {"time": "2024-07-12 19:45:00", "region": "eu-west", "response_time": 31.52390833333333}, {"time": "2024-07-12 20:00:00", "region": "eu-west", "response_time": 27.846070666666666}, {"time": "2024-07-12 20:15:00", "region": "eu-west", "response_time": 21.26520633333333}, {"time": "2024-07-12 20:30:00", "region": "eu-west", "response_time": 21.748649666666665}, {"time": "2024-07-12 20:45:00", "region": "eu-west", "response_time": 34.632471666666675}, {"time": "2024-07-12 21:00:00", "region": "eu-west", "response_time": 34.728894333333336}, {"time": "2024-07-12 21:15:00", "region": "eu-west", "response_time": 27.676286333333337}, {"time": "2024-07-12 21:30:00", "region": "eu-west", "response_time": 18.059876666666664}, {"time": "2024-07-12 21:45:00", "region": "eu-west", "response_time": 27.442142}, {"time": "2024-07-12 22:00:00", "region": "eu-west", "response_time": 34.90286833333334}, {"time": "2024-07-12 22:15:00", "region": "eu-west", "response_time": 19.062679666666668}, {"time": "2024-07-12 22:30:00", "region": "eu-west", "response_time": 32.546704000000005}, {"time": "2024-07-12 22:45:00", "region": "eu-west", "response_time": 28.884229}, {"time": "2024-07-12 23:00:00", "region": "eu-west", "response_time": 24.619705333333336}, {"time": "2024-07-12 23:15:00", "region": "eu-west", "response_time": 47.46731266666667}, {"time": "2024-07-12 23:30:00", "region": "eu-west", "response_time": 36.243250999999994}, {"time": "2024-07-12 23:45:00", "region": "eu-west", "response_time": 29.745552999999997}, {"time": "2024-07-12 18:00:00", "region": "us-east", "response_time": 66.66306366666667}, {"time": "2024-07-12 18:15:00", "region": "us-east", "response_time": 74.41809133333334}, {"time": "2024-07-12 18:30:00", "region": "us-east", "response_time": 84.20043566666666}, {"time": "2024-07-12 18:45:00", "region": "us-east", "response_time": 61.066172333333334}, {"time": "2024-07-12 19:00:00", "region": "us-east", "response_time": 64.27104033333333}, {"time": "2024-07-12 19:15:00", "region": "us-east", "response_time": 69.25871500000001}, {"time": "2024-07-12 19:30:00", "region": "us-east", "response_time": 70.23207766666667}, {"time": "2024-07-12 19:45:00", "region": "us-east", "response_time": 83.027972}, {"time": "2024-07-12 20:00:00", "region": "us-east", "response_time": 72.709445}, {"time": "2024-07-12 20:15:00", "region": "us-east", "response_time": 64.87308633333333}, {"time": "2024-07-12 20:30:00", "region": "us-east", "response_time": 66.98122400000001}, {"time": "2024-07-12 20:45:00", "region": "us-east", "response_time": 66.26356366666668}, {"time": "2024-07-12 21:00:00", "region": "us-east", "response_time": 64.89281666666668}, {"time": "2024-07-12 21:15:00", "region": "us-east", "response_time": 71.364715}, {"time": "2024-07-12 21:30:00", "region": "us-east", "response_time": 68.226996}, {"time": "2024-07-12 21:45:00", "region": "us-east", "response_time": 69.87753066666667}, {"time": "2024-07-12 22:00:00", "region": "us-east", "response_time": 69.41438733333334}, {"time": "2024-07-12 22:15:00", "region": "us-east", "response_time": 52.57870833333334}, {"time": "2024-07-12 22:30:00", "region": "us-east", "response_time": 72.52145466666667}, {"time": "2024-07-12 22:45:00", "region": "us-east", "response_time": 68.72467066666667}, {"time": "2024-07-12 23:00:00", "region": "us-east", "response_time": 65.48224066666668}, {"time": "2024-07-12 23:15:00", "region": "us-east", "response_time": 57.633121333333335}, {"time": "2024-07-12 23:30:00", "region": "us-east", "response_time": 68.56815333333333}, {"time": "2024-07-12 23:45:00", "region": "us-east", "response_time": 53.542970000000004}, {"time": "2024-07-12 18:00:00", "region": "us-west", "response_time": 15.884871999999998}, {"time": "2024-07-12 18:15:00", "region": "us-west", "response_time": 17.859323}, {"time": "2024-07-12 18:30:00", "region": "us-west", "response_time": 20.34068533333333}, {"time": "2024-07-12 18:45:00", "region": "us-west", "response_time": 19.079936333333336}, {"time": "2024-07-12 19:00:00", "region": "us-west", "response_time": 16.905342333333333}, {"time": "2024-07-12 19:15:00", "region": "us-west", "response_time": 15.992227333333334}, {"time": "2024-07-12 19:30:00", "region": "us-west", "response_time": 15.790613666666669}, {"time": "2024-07-12 19:45:00", "region": "us-west", "response_time": 14.704772}, {"time": "2024-07-12 20:00:00", "region": "us-west", "response_time": 20.255296666666666}, {"time": "2024-07-12 20:15:00", "region": "us-west", "response_time": 19.654747000000004}, {"time": "2024-07-12 20:30:00", "region": "us-west", "response_time": 19.093591666666665}, {"time": "2024-07-12 20:45:00", "region": "us-west", "response_time": 17.518066666666666}, {"time": "2024-07-12 21:00:00", "region": "us-west", "response_time": 15.255042000000001}, {"time": "2024-07-12 21:15:00", "region": "us-west", "response_time": 17.068759999999997}, {"time": "2024-07-12 21:30:00", "region": "us-west", "response_time": 18.498165}, {"time": "2024-07-12 21:45:00", "region": "us-west", "response_time": 18.427982666666665}, {"time": "2024-07-12 22:00:00", "region": "us-west", "response_time": 19.361341333333336}, {"time": "2024-07-12 22:15:00", "region": "us-west", "response_time": 19.341583666666665}, {"time": "2024-07-12 22:30:00", "region": "us-west", "response_time": 20.214801333333334}, {"time": "2024-07-12 22:45:00", "region": "us-west", "response_time": 17.064359666666665}, {"time": "2024-07-12 23:00:00", "region": "us-west", "response_time": 14.601148333333333}, {"time": "2024-07-12 23:15:00", "region": "us-west", "response_time": 17.141703333333332}, {"time": "2024-07-12 23:30:00", "region": "us-west", "response_time": 17.49619333333333}, {"time": "2024-07-12 23:45:00", "region": "us-west", "response_time": 18.459112333333334}], "origin_response_times": [{"time": "2024-07-12 18:00:00", "region": "apac", "response_time": 944.9370899999999}, {"time": "2024-07-12 18:15:00", "region": "apac", "response_time": 974.7665206666666}, {"time": "2024-07-12 18:30:00", "region": "apac", "response_time": 1003.105795}, {"time": "2024-07-12 18:45:00", "region": "apac", "response_time": 968.3681316666667}, {"time": "2024-07-12 19:00:00", "region": "apac", "response_time": 964.5272553333334}, {"time": "2024-07-12 19:15:00", "region": "apac", "response_time": 969.4000946666666}, {"time": "2024-07-12 19:30:00", "region": "apac", "response_time": 968.0235076666667}, {"time": "2024-07-12 19:45:00", "region": "apac", "response_time": 926.1295179999998}, {"time": "2024-07-12 20:00:00", "region": "apac", "response_time": 930.3756486666666}, {"time": "2024-07-12 20:15:00", "region": "apac", "response_time": 936.9463319999999}, {"time": "2024-07-12 20:30:00", "region": "apac", "response_time": 930.8147170000001}, {"time": "2024-07-12 20:45:00", "region": "apac", "response_time": 921.8804353333333}, {"time": "2024-07-12 21:00:00", "region": "apac", "response_time": 933.1018246666667}, {"time": "2024-07-12 21:15:00", "region": "apac", "response_time": 924.2929476666667}, {"time": "2024-07-12 21:30:00", "region": "apac", "response_time": 933.5315566666666}, {"time": "2024-07-12 21:45:00", "region": "apac", "response_time": 940.6275296666666}, {"time": "2024-07-12 22:00:00", "region": "apac", "response_time": 926.9365323333334}, {"time": "2024-07-12 22:15:00", "region": "apac", "response_time": 927.1681319999999}, {"time": "2024-07-12 22:30:00", "region": "apac", "response_time": 964.3264883333333}, {"time": "2024-07-12 22:45:00", "region": "apac", "response_time": 931.9104343333335}, {"time": "2024-07-12 23:00:00", "region": "apac", "response_time": 956.5878866666667}, {"time": "2024-07-12 23:15:00", "region": "apac", "response_time": 953.8477923333334}, {"time": "2024-07-12 23:30:00", "region": "apac", "response_time": 937.411677}, {"time": "2024-07-12 23:45:00", "region": "apac", "response_time": 944.4905423333335}, {"time": "2024-07-12 18:00:00", "region": "eu-west", "response_time": 32.18385233333334}, {"time": "2024-07-12 18:15:00", "region": "eu-west", "response_time": 33.92903366666666}, {"time": "2024-07-12 18:30:00", "region": "eu-west", "response_time": 29.194018666666665}, {"time": "2024-07-12 18:45:00", "region": "eu-west", "response_time": 30.975402}, {"time": "2024-07-12 19:00:00", "region": "eu-west", "response_time": 26.565641}, {"time": "2024-07-12 19:15:00", "region": "eu-west", "response_time": 31.84105733333333}, {"time": "2024-07-12 19:30:00", "region": "eu-west", "response_time": 38.33797333333334}, {"time": "2024-07-12 19:45:00", "region": "eu-west", "response_time": 29.265744}, {"time": "2024-07-12 20:00:00", "region": "eu-west", "response_time": 25.547766}, {"time": "2024-07-12 20:15:00", "region": "eu-west", "response_time": 28.23880766666666}, {"time": "2024-07-12 20:30:00", "region": "eu-west", "response_time": 32.791964666666665}, {"time": "2024-07-12 20:45:00", "region": "eu-west", "response_time": 29.061001333333337}, {"time": "2024-07-12 21:00:00", "region": "eu-west", "response_time": 30.250427}, {"time": "2024-07-12 21:15:00", "region": "eu-west", "response_time": 28.668249333333335}, {"time": "2024-07-12 21:30:00", "region": "eu-west", "response_time": 27.460530333333335}, {"time": "2024-07-12 21:45:00", "region": "eu-west", "response_time": 38.678849}, {"time": "2024-07-12 22:00:00", "region": "eu-west", "response_time": 28.495473333333337}, {"time": "2024-07-12 22:15:00", "region": "eu-west", "response_time": 31.43802833333333}, {"time": "2024-07-12 22:30:00", "region": "eu-west", "response_time": 27.863008333333337}, {"time": "2024-07-12 22:45:00", "region": "eu-west", "response_time": 28.17840833333333}, {"time": "2024-07-12 23:00:00", "region": "eu-west", "response_time": 31.936651333333337}, {"time": "2024-07-12 23:15:00", "region": "eu-west", "response_time": 30.704458}, {"time": "2024-07-12 23:30:00", "region": "eu-west", "response_time": 32.36127466666667}, {"time": "2024-07-12 23:45:00", "region": "eu-west", "response_time": 29.957979000000005}, {"time": "2024-07-12 18:00:00", "region": "us-east", "response_time": 412.215424}, {"time": "2024-07-12 18:15:00", "region": "us-east", "response_time": 418.31453066666666}, {"time": "2024-07-12 18:30:00", "region": "us-east", "response_time": 417.02011733333336}, {"time": "2024-07-12 18:45:00", "region": "us-east", "response_time": 407.05691433333334}, {"time": "2024-07-12 19:00:00", "region": "us-east", "response_time": 406.55231399999997}, {"time": "2024-07-12 19:15:00", "region": "us-east", "response_time": 419.5473570000001}, {"time": "2024-07-12 19:30:00", "region": "us-east", "response_time": 414.401721}, {"time": "2024-07-12 19:45:00", "region": "us-east", "response_time": 418.6661676666667}, {"time": "2024-07-12 20:00:00", "region": "us-east", "response_time": 426.2851576666667}, {"time": "2024-07-12 20:15:00", "region": "us-east", "response_time": 405.100814}, {"time": "2024-07-12 20:30:00", "region": "us-east", "response_time": 406.9807876666667}, {"time": "2024-07-12 20:45:00", "region": "us-east", "response_time": 411.6666783333334}, {"time": "2024-07-12 21:00:00", "region": "us-east", "response_time": 397.6009276666666}, {"time": "2024-07-12 21:15:00", "region": "us-east", "response_time": 414.28306900000007}, {"time": "2024-07-12 21:30:00", "region": "us-east", "response_time": 418.00815266666666}, {"time": "2024-07-12 21:45:00", "region": "us-east", "response_time": 415.28893633333337}, {"time": "2024-07-12 22:00:00", "region": "us-east", "response_time": 423.76225133333327}, {"time": "2024-07-12 22:15:00", "region": "us-east", "response_time": 420.89321233333334}, {"time": "2024-07-12 22:30:00", "region": "us-east", "response_time": 407.0365806666666}, {"time": "2024-07-12 22:45:00", "region": "us-east", "response_time": 421.12402499999996}, {"time": "2024-07-12 23:00:00", "region": "us-east", "response_time": 399.7128853333333}, {"time": "2024-07-12 23:15:00", "region": "us-east", "response_time": 403.1447613333334}, {"time": "2024-07-12 23:30:00", "region": "us-east", "response_time": 410.64243066666666}, {"time": "2024-07-12 23:45:00", "region": "us-east", "response_time": 411.965246}, {"time": "2024-07-12 18:00:00", "region": "us-west", "response_time": 589.4253186666667}, {"time": "2024-07-12 18:15:00", "region": "us-west", "response_time": 607.9630646666666}, {"time": "2024-07-12 18:30:00", "region": "us-west", "response_time": 600.014699}, {"time": "2024-07-12 18:45:00", "region": "us-west", "response_time": 1207.826252}, {"time": "2024-07-12 19:00:00", "region": "us-west", "response_time": 612.1822096666666}, {"time": "2024-07-12 19:15:00", "region": "us-west", "response_time": 615.5047050000001}, {"time": "2024-07-12 19:30:00", "region": "us-west", "response_time": 606.7204620000001}, {"time": "2024-07-12 19:45:00", "region": "us-west", "response_time": 593.7956933333334}, {"time": "2024-07-12 20:00:00", "region": "us-west", "response_time": 606.5973486666668}, {"time": "2024-07-12 20:15:00", "region": "us-west", "response_time": 610.268382}, {"time": "2024-07-12 20:30:00", "region": "us-west", "response_time": 619.69509}, {"time": "2024-07-12 20:45:00", "region": "us-west", "response_time": 607.8448403333333}, {"time": "2024-07-12 21:00:00", "region": "us-west", "response_time": 604.222814}, {"time": "2024-07-12 21:15:00", "region": "us-west", "response_time": 599.4849346666666}, {"time": "2024-07-12 21:30:00", "region": "us-west", "response_time": 603.1158273333333}, {"time": "2024-07-12 21:45:00", "region": "us-west", "response_time": 610.2455416666667}, {"time": "2024-07-12 22:00:00", "region": "us-west", "response_time": 599.407267}, {"time": "2024-07-12 22:15:00", "region": "us-west", "response_time": 603.1402173333333}, {"time": "2024-07-12 22:30:00", "region": "us-west", "response_time": 600.231604}, {"time": "2024-07-12 22:45:00", "region": "us-west", "response_time": 603.774831}, {"time": "2024-07-12 23:00:00", "region": "us-west", "response_time": 595.7035296666668}, {"time": "2024-07-12 23:15:00", "region": "us-west", "response_time": 605.466485}, {"time": "2024-07-12 23:30:00", "region": "us-west", "response_time": 607.9491680000001}, {"time": "2024-07-12 23:45:00", "region": "us-west", "response_time": 601.8119196666667}], "edge_responses_by_region": [{"region": "apac", "min": 12.822743, "max": 93.78721399999999, "mean": 39.121766, "p95": 91.24324809999999}, {"region": "eu-west", "min": 14.124075, "max": 74.3695, "mean": 31.18859977777778, "p95": 66.13344139999997}, {"region": "us-east", "min": 44.200057, "max": 114.352908, "mean": 67.78302715277778, "p95": 92.9344399}, {"region": "us-west", "min": 12.617919, "max": 29.794749, "mean": 17.750402791666666, "p95": 25.900817399999994}], "origin_responses_by_region": [{"region": "apac", "min": 902.3861370000001, "max": 1062.5134059999998, "mean": 946.3961829166666, "p95": 995.5625222}, {"region": "eu-west", "min": 19.727371, "max": 41.971944, "mean": 30.580233291666666, "p95": 40.646249100000006}, {"region": "us-east", "min": 392.08750599999996, "max": 440.627421, "mean": 412.8029359166666, "p95": 432.35301319999996}, {"region": "us-west", "min": 585.078719, "max": 2397.2826010000003, "mean": 629.6830085277776, "p95": 620.7486372}], "services": [["https://www.bentasker.co.uk/", "Unknown"], ["https://mastodon.bentasker.co.uk/", "Unknown"]]}